dash_gql_client/GQLClient.py
dash_gql_client/__init__.py
dash_gql_client/_imports_.py
dash_gql_client/async-GQLClient.js
dash_gql_client/async-GQLClient.js.map
dash_gql_client/dash_gql_client.min.js
dash_gql_client/dash_gql_client.min.js.map
dash_gql_client/metadata.json
dash_gql_client/package-info.json
dash_gql_client-0.0.4.dist-info/LICENSE
dash_gql_client-0.0.4.dist-info/METADATA
dash_gql_client-0.0.4.dist-info/WHEEL
dash_gql_client-0.0.4.dist-info/top_level.txt
dash_gql_client-0.0.4.dist-info/RECORD
