Metadata-Version: 2.1
Name: dash-gql-client
Version: 0.0.4
Summary: A simple GraphQL Client wrapped as a Dash Component
Author: Niklas Laufkoetter <niklas@laufkoetter.info>
License: MIT
Classifier: Framework :: Dash
License-File: LICENSE
